oxdork/__init__.py
oxdork/banner.py
oxdork/colors.py
oxdork/default.py
oxdork/main.py
oxdork/minimal.py
oxdork/output.py
oxdork-2022.2.2.0.dist-info/LICENSE
oxdork-2022.2.2.0.dist-info/METADATA
oxdork-2022.2.2.0.dist-info/WHEEL
oxdork-2022.2.2.0.dist-info/entry_points.txt
oxdork-2022.2.2.0.dist-info/top_level.txt
oxdork-2022.2.2.0.dist-info/RECORD
