Metadata-Version: 2.1
Name: oxdork
Version: 2022.2.2.0
Summary: Google dorking tool
Home-page: https://github.com/rly0nheart/oxdork
Author: Richard Mwewa
Author-email: richardmwewa@duck.com
License: MIT License
Platform: UNKNOWN
Classifier: Intended Audience :: Information Technology
Classifier: License :: OSI Approved :: MIT License
Classifier: Operating System :: POSIX :: Linux
Classifier: Natural Language :: English
Classifier: Programming Language :: Python :: 3
License-File: LICENSE
Requires-Dist: google
Requires-Dist: requests
